{
    "project_logo": "../logo.svg",
    "project_favicon": "favicon.png",
    "project_name": "Saturn V",
    "project_url": null,
    "copyright_start_year": null,
    "client_name": null,
    "client_url": null,
    "creators": [
        {
            "name": "Marcio Gasparotto",
            "url": "http://github.com/marcio"
        },
        {
            "name": "Synchro",
            "url": "http://synchro.com.br"
        }
    ],
    "theme": {
        "border_color": "#E0E6ED",
        "highlight_color": "#F9FAFC",
        "brand_color": "#1a7bba",
        "background_color": "#FFFFFF",
        "code_highlight_theme": "github",
        "override_code_highlight_bg": "#F9FAFC",
        "sample_dark_background": "#333333",
        "show_project_name": false,
        "show_version": false,
        "max_width": null
    },
    "assets": {
        "css": [
            "../css/saturn-v.css"
        ],
        "js": []
    },
    "font_libraries": {
        "typekit_code": null,
        "typography_web_fonts": null,
        "google_web_fonts": null
    },
    "content": {
        "show_first_page_on_load": true,
        "title": "Overview",
        "pages": [
            {
                "name": "introduction",
                "title": "Introduction",
                "file": "./pages/intro.md"
            }
        ]
    },
    "groups": [
        {
            "name": "colors",
            "title": "Colors",
            "components": [
                {
                    "group": "colors",
                    "name": "color-palette",
                    "title": "Colors",
                    "type": "colors",
                    "colors": [
                      "#FFFFFF",
                      "#000000",
                      "#F44336",
                      "#FFEBEE",
                      "#FFCDD2",
                      "#EF9A9A",
                      "#E57373",
                      "#EF5350",
                      "#E53935",
                      "#D32F2F",
                      "#C62828",
                      "#B71C1C",
                      "#FF8A80",
                      "#FF5252",
                      "#FF1744",
                      "#D50000",
                      "#E91E63",
                      "#FCE4EC",
                      "#F8BBD0",
                      "#F48FB1",
                      "#F06292",
                      "#EC407A",
                      "#D81B60",
                      "#C2185B",
                      "#AD1457",
                      "#880E4F",
                      "#FF80AB",
                      "#FF4081",
                      "#F50057",
                      "#C51162",
                      "#673AB7",
                      "#EDE7F6",
                      "#D1C4E9",
                      "#B39DDB",
                      "#9575CD",
                      "#7E57C2",
                      "#5E35B1",
                      "#512DA8",
                      "#4527A0",
                      "#311B92",
                      "#B388FF",
                      "#7C4DFF",
                      "#651FFF",
                      "#6200EA",
                      "#3F51B5",
                      "#E8EAF6",
                      "#C5CAE9",
                      "#9FA8DA",
                      "#7986CB",
                      "#5C6BC0",
                      "#3949AB",
                      "#303F9F",
                      "#283593",
                      "#1A237E",
                      "#8C9EFF",
                      "#536DFE",
                      "#3D5AFE",
                      "#304FFE",
                      "#2196F3",
                      "#E3F2FD",
                      "#BBDEFB",
                      "#90CAF9",
                      "#64B5F6",
                      "#42A5F5",
                      "#1E88E5",
                      "#1976D2",
                      "#1565C0",
                      "#0D47A1",
                      "#82B1FF",
                      "#448AFF",
                      "#2979FF",
                      "#2962FF",
                      "#4CAF50",
                      "#E8F5E9",
                      "#C8E6C9",
                      "#A5D6A7",
                      "#81C784",
                      "#66BB6A",
                      "#43A047",
                      "#388E3C",
                      "#2E7D32",
                      "#1B5E20",
                      "#B9F6CA",
                      "#69F0AE",
                      "#00E676",
                      "#00C853",
                      "#FFEB3B",
                      "#FFFDE7",
                      "#FFF9C4",
                      "#FFF59D",
                      "#FFF176",
                      "#FFEE58",
                      "#FDD835",
                      "#FBC02D",
                      "#F9A825",
                      "#F57F17",
                      "#FFFF8D",
                      "#FFFF00",
                      "#FFEA00",
                      "#FFD600",
                      "#FFC107",
                      "#FFF8E1",
                      "#FFECB3",
                      "#FFE082",
                      "#FFD54F",
                      "#FFCA28",
                      "#FFB300",
                      "#FFA000",
                      "#FF8F00",
                      "#FF6F00",
                      "#FFE57F",
                      "#FFD740",
                      "#FFC400",
                      "#FFAB00",
                      "#FF9800",
                      "#FFF3E0",
                      "#FFE0B2",
                      "#FFCC80",
                      "#FFB74D",
                      "#FFA726",
                      "#FB8C00",
                      "#F57C00",
                      "#EF6C00",
                      "#E65100",
                      "#FFD180",
                      "#FFAB40",
                      "#FF9100",
                      "#FF6D00",
                      "#FF5722",
                      "#FBE9E7",
                      "#FFCCBC",
                      "#FFAB91",
                      "#FF8A65",
                      "#FF7043",
                      "#F4511E",
                      "#E64A19",
                      "#D84315",
                      "#BF360C",
                      "#FF9E80",
                      "#FF6E40",
                      "#FF3D00",
                      "#DD2C00",
                      "#795548",
                      "#EFEBE9",
                      "#D7CCC8",
                      "#BCAAA4",
                      "#A1887F",
                      "#8D6E63",
                      "#6D4C41",
                      "#5D4037",
                      "#4E342E",
                      "#3E2723",
                      "#9E9E9E",
                      "#FAFAFA",
                      "#F5F5F5",
                      "#EEEEEE",
                      "#E0E0E0",
                      "#BDBDBD",
                      "#757575",
                      "#616161",
                      "#424242",
                      "#212121",
                      "#607D8B",
                      "#ECEFF1",
                      "#CFD8DC",
                      "#B0BEC5",
                      "#90A4AE",
                      "#78909C",
                      "#546E7A",
                      "#455A64",
                      "#37474F",
                      "#263238",
                      "#C0C0C0",
                      "#FDE0DC",
                      "#F9BDBB",
                      "#F3E5F5",
                      "#E1BEE7",
                      "#E7E9FD",
                      "#D0D9FF",
                      "#E1F5FE",
                      "#B3E5FC",
                      "#E0F7FA",
                      "#B2EBF2",
                      "#E0F2F1",
                      "#B2DFDB",
                      "#D0F8CE",
                      "#A3E9A4",
                      "#F1F8E9",
                      "#DCEDC8",
                      "#F9FBE7",
                      "#F0F4C3"
                    ]
                }
            ]
        },
        {
            "name": "layout",
            "title": "Layout",
            "components": [
                {
                    "group": "layout",
                    "name": "grid",
                    "title": "Grid System",
                    "options": {
                        "sample_dark_background": false
                    }
                }
            ]
        },
        {
            "name": "table",
            "title": "Tables",
            "components": [
                {
                    "group": "table",
                    "name": "default",
                    "title": "Table"
                },
                {
                    "group": "table",
                    "name": "hover",
                    "title": "Table with hover "
                },
                {
                    "group": "table",
                    "name": "borders",
                    "title": "Table with borders"
                },
                {
                    "group": "table",
                    "name": "shadow",
                    "title": "Table with  shadow"
                },
                {
                    "group": "table",
                    "name": "condensed",
                    "title": "Table Condensed"
                }
            ]
        },
        {
            "name": "cards",
            "title": "Cards",
            "components": [
                {
                    "group": "cards",
                    "name": "default",
                    "title": "Default Card",
                    "width": "half"
                },
                {
                    "group": "cards",
                    "name": "decorated",
                    "title": "Decorated Card",
                    "width": "half"
                }
            ]
        }
    ],
    "version": "1.5.10"
}
